fram/__init__.py
fram-0.0.0.dist-info/METADATA
fram-0.0.0.dist-info/WHEEL
fram-0.0.0.dist-info/top_level.txt
fram-0.0.0.dist-info/RECORD
