Metadata-Version: 2.4
Name: fram
Version: 0.0.0
Summary: Coming soon...
Author-email: NVE <alro@nve.no>
